MANIFEST.in
README
setup.py
bin/filekasten
filekasten/__init__.py
filekasten/breadcrumbs.py
filekasten/browser.py
filekasten/clean_missing_files.py
filekasten/components.py
filekasten/config.py
filekasten/editor.py
filekasten/exgest_flat_files.py
filekasten/ingest_flat_files.py
filekasten/journal.py
filekasten/maintenance.py
filekasten/models.py
filekasten/search.py
filekasten/web.py
filekasten.egg-info/PKG-INFO
filekasten.egg-info/SOURCES.txt
filekasten.egg-info/dependency_links.txt
filekasten.egg-info/requires.txt
filekasten.egg-info/top_level.txt
filekasten/components/Breadcrumbs/Breadcrumbs.html
filekasten/components/Breadcrumbs/Breadcrumbs.js
filekasten/components/EntryListing/EntryListing.html
filekasten/components/JournalEntry/JournalEntry.mustache
filekasten/components/NVViewer/NVViewer.html
filekasten/components/PageFinder/PageFinder.html
filekasten/components/PageFinder/PageFinder.js
filekasten/components/PageListing/PageListing.html
filekasten/components/SearchBar/SearchBar.js
filekasten/components/SearchBar/SearchBar.mustache
filekasten/components/SettingsPage/SettingsPage.js
filekasten/components/Typeahead/Typeahead.html
filekasten/components/Typeahead/Typeahead.js
filekasten/components/Typeahead/typeahead.jquery.js
filekasten/components/WikiPage/WikiPage.js
filekasten/md_ext/__init__.py
filekasten/md_ext/wikilinks.py
filekasten/md_ext/x_lists.py
filekasten/static/bootstrap.css
filekasten/static/bootstrap.min.css
filekasten/static/jquery-3.3.1.min.js
filekasten/static/main.css
filekasten/static/reset.css
filekasten/static/scrollers.css
filekasten/templates/footer.html
filekasten/templates/header.html
filekasten/templates/index.html
filekasten/templates/jrnl_page.html
filekasten/templates/layout.html
filekasten/templates/pagefinder.html
filekasten/templates/pagelisting.html
filekasten/templates/search_results.html
filekasten/templates/searchbar.html
filekasten/templates/settings.html
filekasten/templates/todo_page.html
filekasten/templates/wiki_append.html
filekasten/templates/wiki_edit.html
filekasten/templates/wiki_page.html
filekasten/templates/wiki_select_page.html