Metadata-Version: 1.0
Name: filekasten
Version: 0.0.2
Summary: a personal file note manager
Home-page: http://github.com/okayzed/filekasten
Author: okay
Author-email: okay.zed+jt@gmail.com
License: MIT
Platform: UNKNOWN
